magic/__init__.py
magic/magic.py
convert_string_to_number-0.1.3.dist-info/LICENSE
convert_string_to_number-0.1.3.dist-info/WHEEL
convert_string_to_number-0.1.3.dist-info/METADATA
convert_string_to_number-0.1.3.dist-info/RECORD
