Metadata-Version: 2.1
Name: convert-string-to-number
Version: 0.1.3
Summary: Convert string to number
Author: NamTH
Author-email: namth2302@gmail.com
Requires-Python: >=3.6.2,<4.0.0
Classifier: Programming Language :: Python :: 3
Classifier: Programming Language :: Python :: 3.10
Classifier: Programming Language :: Python :: 3.7
Classifier: Programming Language :: Python :: 3.8
Classifier: Programming Language :: Python :: 3.9
